<?xml version="1.0" encoding="utf-8"?>
<!DOCTYPE Map[]>
<Map srs="+proj=merc +a=6378137 +b=6378137 +lat_ts=0.0 +lon_0=0.0 +x_0=0.0 +y_0=0.0 +k=1.0 +units=m +nadgrids=@null +wktext +no_defs +over" background-color="#ffffff">

<Parameters>
  <Parameter name="attribution"><![CDATA[<a href='https://www.mapbox.com/about/maps/' target='_blank'>&copy; Mapbox &copy; OpenStreetMap</a> <a class='mapbox-improve-map' href='https://www.mapbox.com/map-feedback/' target='_blank'>Improve this map</a>]]></Parameter>
  <Parameter name="bounds">-180,-85.0511,180,85.0511</Parameter>
  <Parameter name="center">-87.9785,38.4106,5</Parameter>
  <Parameter name="format">png8:m=h</Parameter>
  <Parameter name="maxzoom">7</Parameter>
  <Parameter name="minzoom">3</Parameter>
  <Parameter name="name"><![CDATA[oregon trail]]></Parameter>
  <Parameter name="source"><![CDATA[mapbox:///katiekowalsky.0fa04a37,katiekowalsky.e400dc40,mapbox.mapbox-streets-v5]]></Parameter>
</Parameters>


<Style name="Admin0_Polygons" filter-mode="first">
  <Rule>
    <MaxScaleDenominator>25000000</MaxScaleDenominator>
    <MinScaleDenominator>12500000</MinScaleDenominator>
    <LineSymbolizer stroke-width="1.25" stroke="#000000" />
  </Rule>
  <Rule>
    <MaxScaleDenominator>50000000</MaxScaleDenominator>
    <MinScaleDenominator>25000000</MinScaleDenominator>
    <LineSymbolizer stroke-width="1" stroke="#000000" />
  </Rule>
  <Rule>
    <MaxScaleDenominator>100000000</MaxScaleDenominator>
    <MinScaleDenominator>50000000</MinScaleDenominator>
    <LineSymbolizer stroke-width="0.75" stroke="#000000" />
  </Rule>
  <Rule>
    <LineSymbolizer stroke="#000000" stroke-width="1.5" />
  </Rule>
</Style>
<Layer name="Admin0_Polygons"
  srs="+proj=merc +a=6378137 +b=6378137 +lat_ts=0.0 +lon_0=0.0 +x_0=0.0 +y_0=0.0 +k=1.0 +units=m +nadgrids=@null +wktext +no_defs +over">
    <StyleName>Admin0_Polygons</StyleName>  </Layer>

<Style name="LakeHexes" filter-mode="first">
  <Rule>
    <PolygonSymbolizer fill="#0000ff" gamma="0.2" />
  </Rule>
</Style>
<Layer name="LakeHexes"
  srs="+proj=merc +a=6378137 +b=6378137 +lat_ts=0.0 +lon_0=0.0 +x_0=0.0 +y_0=0.0 +k=1.0 +units=m +nadgrids=@null +wktext +no_defs +over">
    <StyleName>LakeHexes</StyleName>  </Layer>

<Style name="Sea" filter-mode="first">
  <Rule>
    <PolygonPatternSymbolizer file="textures/grid2.png" opacity="0.75" />
  </Rule>
</Style>
<Layer name="Sea"
  srs="+proj=merc +a=6378137 +b=6378137 +lat_ts=0.0 +lon_0=0.0 +x_0=0.0 +y_0=0.0 +k=1.0 +units=m +nadgrids=@null +wktext +no_defs +over">
    <StyleName>Sea</StyleName>  </Layer>

<Layer name="LandHexes"
  srs="+proj=merc +a=6378137 +b=6378137 +lat_ts=0.0 +lon_0=0.0 +x_0=0.0 +y_0=0.0 +k=1.0 +units=m +nadgrids=@null +wktext +no_defs +over">
      </Layer>

<Style name="ne_10m_rivers_lake_centerlines" filter-mode="first">
  <Rule>
    <MaxScaleDenominator>25000000</MaxScaleDenominator>
    <Filter>([scalerank] &lt; 4)</Filter>
    <LineSymbolizer stroke-width="2.5" stroke="#0000ff" stroke-linecap="round" stroke-linejoin="round" stroke-dasharray="1, 6" />
  </Rule>
  <Rule>
    <MaxScaleDenominator>50000000</MaxScaleDenominator>
    <MinScaleDenominator>25000000</MinScaleDenominator>
    <Filter>([scalerank] &lt; 4)</Filter>
    <LineSymbolizer stroke-width="2.5" stroke="#0000ff" stroke-linecap="round" stroke-linejoin="round" stroke-dasharray="1, 5" />
  </Rule>
  <Rule>
    <MaxScaleDenominator>100000000</MaxScaleDenominator>
    <MinScaleDenominator>50000000</MinScaleDenominator>
    <Filter>([scalerank] &lt; 4)</Filter>
    <LineSymbolizer stroke-width="2" stroke="#0000ff" stroke-linecap="round" stroke-linejoin="round" stroke-dasharray="1, 4" />
  </Rule>
  <Rule>
    <MaxScaleDenominator>25000000</MaxScaleDenominator>
    <Filter>([scalerank] &lt; 6)</Filter>
    <LineSymbolizer stroke-width="2.5" stroke="#0000ff" stroke-linecap="round" stroke-linejoin="round" stroke-dasharray="1, 6" />
  </Rule>
  <Rule>
    <MaxScaleDenominator>50000000</MaxScaleDenominator>
    <MinScaleDenominator>25000000</MinScaleDenominator>
    <Filter>([scalerank] &lt; 6)</Filter>
    <LineSymbolizer stroke-width="2.5" stroke="#0000ff" stroke-linecap="round" stroke-linejoin="round" stroke-dasharray="1, 5" />
  </Rule>
  <Rule>
    <MaxScaleDenominator>25000000</MaxScaleDenominator>
    <Filter>([scalerank] &lt; 8)</Filter>
    <LineSymbolizer stroke-width="2.5" stroke="#0000ff" stroke-linecap="round" stroke-linejoin="round" stroke-dasharray="1, 6" />
  </Rule>
</Style>
<Layer name="ne_10m_rivers_lake_centerlines"
  srs="+proj=merc +a=6378137 +b=6378137 +lat_ts=0.0 +lon_0=0.0 +x_0=0.0 +y_0=0.0 +k=1.0 +units=m +nadgrids=@null +wktext +no_defs +over">
    <StyleName>ne_10m_rivers_lake_centerlines</StyleName>  </Layer>

<Layer name="landuse"
  srs="+proj=merc +a=6378137 +b=6378137 +lat_ts=0.0 +lon_0=0.0 +x_0=0.0 +y_0=0.0 +k=1.0 +units=m +nadgrids=@null +wktext +no_defs +over">
      </Layer>

<Layer name="waterway"
  srs="+proj=merc +a=6378137 +b=6378137 +lat_ts=0.0 +lon_0=0.0 +x_0=0.0 +y_0=0.0 +k=1.0 +units=m +nadgrids=@null +wktext +no_defs +over">
      </Layer>

<Layer name="water"
  srs="+proj=merc +a=6378137 +b=6378137 +lat_ts=0.0 +lon_0=0.0 +x_0=0.0 +y_0=0.0 +k=1.0 +units=m +nadgrids=@null +wktext +no_defs +over">
      </Layer>

<Layer name="aeroway"
  srs="+proj=merc +a=6378137 +b=6378137 +lat_ts=0.0 +lon_0=0.0 +x_0=0.0 +y_0=0.0 +k=1.0 +units=m +nadgrids=@null +wktext +no_defs +over">
      </Layer>

<Layer name="barrier_line"
  srs="+proj=merc +a=6378137 +b=6378137 +lat_ts=0.0 +lon_0=0.0 +x_0=0.0 +y_0=0.0 +k=1.0 +units=m +nadgrids=@null +wktext +no_defs +over">
      </Layer>

<Layer name="building"
  srs="+proj=merc +a=6378137 +b=6378137 +lat_ts=0.0 +lon_0=0.0 +x_0=0.0 +y_0=0.0 +k=1.0 +units=m +nadgrids=@null +wktext +no_defs +over">
      </Layer>

<Layer name="landuse_overlay"
  srs="+proj=merc +a=6378137 +b=6378137 +lat_ts=0.0 +lon_0=0.0 +x_0=0.0 +y_0=0.0 +k=1.0 +units=m +nadgrids=@null +wktext +no_defs +over">
      </Layer>

<Layer name="tunnel"
  srs="+proj=merc +a=6378137 +b=6378137 +lat_ts=0.0 +lon_0=0.0 +x_0=0.0 +y_0=0.0 +k=1.0 +units=m +nadgrids=@null +wktext +no_defs +over">
      </Layer>

<Layer name="road"
  srs="+proj=merc +a=6378137 +b=6378137 +lat_ts=0.0 +lon_0=0.0 +x_0=0.0 +y_0=0.0 +k=1.0 +units=m +nadgrids=@null +wktext +no_defs +over">
      </Layer>

<Layer name="bridge"
  group-by="layer"
  srs="+proj=merc +a=6378137 +b=6378137 +lat_ts=0.0 +lon_0=0.0 +x_0=0.0 +y_0=0.0 +k=1.0 +units=m +nadgrids=@null +wktext +no_defs +over">
      </Layer>

<Layer name="admin"
  srs="+proj=merc +a=6378137 +b=6378137 +lat_ts=0.0 +lon_0=0.0 +x_0=0.0 +y_0=0.0 +k=1.0 +units=m +nadgrids=@null +wktext +no_defs +over">
      </Layer>

<Layer name="country_label_line"
  srs="+proj=merc +a=6378137 +b=6378137 +lat_ts=0.0 +lon_0=0.0 +x_0=0.0 +y_0=0.0 +k=1.0 +units=m +nadgrids=@null +wktext +no_defs +over">
      </Layer>

<Style name="country_label" filter-mode="first">
  <Rule>
    <MaxScaleDenominator>25000000</MaxScaleDenominator>
    <Filter>([scalerank] = 5)</Filter>
    <TextSymbolizer size="12" face-name="Call Three OT Regular" fill="#000000" halo-fill="#ffffff" halo-radius="1.5" allow-overlap="false" ><![CDATA[[name_en]]]></TextSymbolizer>
  </Rule>
  <Rule>
    <MaxScaleDenominator>50000000</MaxScaleDenominator>
    <MinScaleDenominator>25000000</MinScaleDenominator>
    <Filter>([scalerank] = 5)</Filter>
    <TextSymbolizer size="10" face-name="Call Three OT Regular" fill="#000000" halo-fill="#ffffff" halo-radius="1" allow-overlap="false" ><![CDATA[[name_en]]]></TextSymbolizer>
  </Rule>
  <Rule>
    <MaxScaleDenominator>25000000</MaxScaleDenominator>
    <Filter>([scalerank] = 4)</Filter>
    <TextSymbolizer size="13" face-name="Call Three OT Regular" fill="#000000" halo-fill="#ffffff" halo-radius="2" allow-overlap="false" ><![CDATA[[name_en]]]></TextSymbolizer>
  </Rule>
  <Rule>
    <MaxScaleDenominator>50000000</MaxScaleDenominator>
    <MinScaleDenominator>25000000</MinScaleDenominator>
    <Filter>([scalerank] = 4)</Filter>
    <TextSymbolizer size="12" face-name="Call Three OT Regular" fill="#000000" halo-fill="#ffffff" halo-radius="1.25" allow-overlap="false" ><![CDATA[[name_en]]]></TextSymbolizer>
  </Rule>
  <Rule>
    <MaxScaleDenominator>100000000</MaxScaleDenominator>
    <MinScaleDenominator>50000000</MinScaleDenominator>
    <Filter>([scalerank] = 4)</Filter>
    <TextSymbolizer size="7" face-name="Call Three OT Regular" fill="#000000" halo-fill="#ffffff" halo-radius="1" allow-overlap="false" ><![CDATA[[name_en]]]></TextSymbolizer>
  </Rule>
  <Rule>
    <MaxScaleDenominator>25000000</MaxScaleDenominator>
    <Filter>([scalerank] = 3)</Filter>
    <TextSymbolizer size="14" face-name="Call Three OT Regular" fill="#000000" halo-fill="#ffffff" halo-radius="2.5" allow-overlap="false" ><![CDATA[[name_en]]]></TextSymbolizer>
  </Rule>
  <Rule>
    <MaxScaleDenominator>50000000</MaxScaleDenominator>
    <MinScaleDenominator>25000000</MinScaleDenominator>
    <Filter>([scalerank] = 3)</Filter>
    <TextSymbolizer size="14" face-name="Call Three OT Regular" fill="#000000" halo-fill="#ffffff" halo-radius="1.5" allow-overlap="false" ><![CDATA[[name_en]]]></TextSymbolizer>
  </Rule>
  <Rule>
    <MaxScaleDenominator>100000000</MaxScaleDenominator>
    <MinScaleDenominator>50000000</MinScaleDenominator>
    <Filter>([scalerank] = 3)</Filter>
    <TextSymbolizer size="8" face-name="Call Three OT Regular" fill="#000000" halo-fill="#ffffff" halo-radius="1.5" allow-overlap="false" ><![CDATA[[name_en]]]></TextSymbolizer>
  </Rule>
  <Rule>
    <MaxScaleDenominator>25000000</MaxScaleDenominator>
    <Filter>([scalerank] = 2)</Filter>
    <TextSymbolizer size="16" face-name="Call Three OT Regular" fill="#000000" halo-fill="#ffffff" halo-radius="3" allow-overlap="false" ><![CDATA[[name_en]]]></TextSymbolizer>
  </Rule>
  <Rule>
    <MaxScaleDenominator>50000000</MaxScaleDenominator>
    <MinScaleDenominator>25000000</MinScaleDenominator>
    <Filter>([scalerank] = 2)</Filter>
    <TextSymbolizer size="16" face-name="Call Three OT Regular" fill="#000000" halo-fill="#ffffff" halo-radius="2" allow-overlap="false" ><![CDATA[[name_en]]]></TextSymbolizer>
  </Rule>
  <Rule>
    <MaxScaleDenominator>100000000</MaxScaleDenominator>
    <MinScaleDenominator>50000000</MinScaleDenominator>
    <Filter>([scalerank] = 2)</Filter>
    <TextSymbolizer size="10" face-name="Call Three OT Regular" fill="#000000" halo-fill="#ffffff" halo-radius="2" allow-overlap="false" ><![CDATA[[name_en]]]></TextSymbolizer>
  </Rule>
  <Rule>
    <MaxScaleDenominator>25000000</MaxScaleDenominator>
    <Filter>([scalerank] = 1)</Filter>
    <TextSymbolizer size="24" face-name="Call Three OT Regular" fill="#000000" halo-fill="#ffffff" halo-radius="3.5" allow-overlap="false" ><![CDATA[[name_en]]]></TextSymbolizer>
  </Rule>
  <Rule>
    <MaxScaleDenominator>50000000</MaxScaleDenominator>
    <MinScaleDenominator>25000000</MinScaleDenominator>
    <Filter>([scalerank] = 1)</Filter>
    <TextSymbolizer size="18" face-name="Call Three OT Regular" fill="#000000" halo-fill="#ffffff" halo-radius="2.5" allow-overlap="false" ><![CDATA[[name_en]]]></TextSymbolizer>
  </Rule>
  <Rule>
    <MaxScaleDenominator>100000000</MaxScaleDenominator>
    <MinScaleDenominator>50000000</MinScaleDenominator>
    <Filter>([scalerank] = 1)</Filter>
    <TextSymbolizer size="12" face-name="Call Three OT Regular" fill="#000000" halo-fill="#ffffff" halo-radius="2.5" allow-overlap="false" ><![CDATA[[name_en]]]></TextSymbolizer>
  </Rule>
</Style>
<Layer name="country_label"
  srs="+proj=merc +a=6378137 +b=6378137 +lat_ts=0.0 +lon_0=0.0 +x_0=0.0 +y_0=0.0 +k=1.0 +units=m +nadgrids=@null +wktext +no_defs +over">
    <StyleName>country_label</StyleName>  </Layer>

<Layer name="marine_label"
  srs="+proj=merc +a=6378137 +b=6378137 +lat_ts=0.0 +lon_0=0.0 +x_0=0.0 +y_0=0.0 +k=1.0 +units=m +nadgrids=@null +wktext +no_defs +over">
      </Layer>

<Layer name="state_label"
  srs="+proj=merc +a=6378137 +b=6378137 +lat_ts=0.0 +lon_0=0.0 +x_0=0.0 +y_0=0.0 +k=1.0 +units=m +nadgrids=@null +wktext +no_defs +over">
      </Layer>

<Style name="place_label-cityicon" filter-mode="first">
  <Rule>
    <MaxScaleDenominator>25000000</MaxScaleDenominator>
    <Filter>([scalerank] = 1) and ([ldir] = 'NW')</Filter>
    <ShieldSymbolizer dx="-4" dy="-4" file="icons/city1.png" unlock-image="true" size="12" face-name="Call Eight OT Regular" placement="point" fill="#000000" halo-fill="#ffffff" halo-radius="1.5" ><![CDATA[[name_en]]]></ShieldSymbolizer>
  </Rule>
  <Rule>
    <MaxScaleDenominator>25000000</MaxScaleDenominator>
    <Filter>([scalerank] = 1) and ([ldir] = 'SW')</Filter>
    <ShieldSymbolizer dx="-4" dy="4" file="icons/city1.png" unlock-image="true" size="12" face-name="Call Eight OT Regular" placement="point" fill="#000000" halo-fill="#ffffff" halo-radius="1.5" ><![CDATA[[name_en]]]></ShieldSymbolizer>
  </Rule>
  <Rule>
    <MaxScaleDenominator>25000000</MaxScaleDenominator>
    <Filter>([scalerank] = 1) and ([ldir] = 'SE')</Filter>
    <ShieldSymbolizer dx="4" dy="4" file="icons/city1.png" unlock-image="true" size="12" face-name="Call Eight OT Regular" placement="point" fill="#000000" halo-fill="#ffffff" halo-radius="1.5" ><![CDATA[[name_en]]]></ShieldSymbolizer>
  </Rule>
  <Rule>
    <MaxScaleDenominator>25000000</MaxScaleDenominator>
    <Filter>([scalerank] = 1) and ([ldir] = 'NE')</Filter>
    <ShieldSymbolizer dx="4" dy="-4" file="icons/city1.png" unlock-image="true" size="12" face-name="Call Eight OT Regular" placement="point" fill="#000000" halo-fill="#ffffff" halo-radius="1.5" ><![CDATA[[name_en]]]></ShieldSymbolizer>
  </Rule>
  <Rule>
    <MaxScaleDenominator>25000000</MaxScaleDenominator>
    <Filter>([scalerank] = 1) and ([ldir] = 'S')</Filter>
    <ShieldSymbolizer dy="8" file="icons/city1.png" unlock-image="true" size="12" face-name="Call Eight OT Regular" placement="point" fill="#000000" halo-fill="#ffffff" halo-radius="1.5" ><![CDATA[[name_en]]]></ShieldSymbolizer>
  </Rule>
  <Rule>
    <MaxScaleDenominator>25000000</MaxScaleDenominator>
    <Filter>([scalerank] = 1) and ([ldir] = 'N')</Filter>
    <ShieldSymbolizer dy="-8" file="icons/city1.png" unlock-image="true" size="12" face-name="Call Eight OT Regular" placement="point" fill="#000000" halo-fill="#ffffff" halo-radius="1.5" ><![CDATA[[name_en]]]></ShieldSymbolizer>
  </Rule>
  <Rule>
    <MaxScaleDenominator>25000000</MaxScaleDenominator>
    <Filter>([scalerank] = 1) and ([ldir] = 'W')</Filter>
    <ShieldSymbolizer dx="-8" file="icons/city1.png" unlock-image="true" size="12" face-name="Call Eight OT Regular" placement="point" fill="#000000" halo-fill="#ffffff" halo-radius="1.5" ><![CDATA[[name_en]]]></ShieldSymbolizer>
  </Rule>
  <Rule>
    <MaxScaleDenominator>25000000</MaxScaleDenominator>
    <Filter>([scalerank] = 1) and ([ldir] = 'E')</Filter>
    <ShieldSymbolizer dx="8" file="icons/city1.png" unlock-image="true" size="12" face-name="Call Eight OT Regular" placement="point" fill="#000000" halo-fill="#ffffff" halo-radius="1.5" ><![CDATA[[name_en]]]></ShieldSymbolizer>
  </Rule>
  <Rule>
    <MaxScaleDenominator>25000000</MaxScaleDenominator>
    <Filter>([scalerank] = 1)</Filter>
    <ShieldSymbolizer file="icons/city1.png" unlock-image="true" size="12" face-name="Call Eight OT Regular" placement="point" fill="#000000" halo-fill="#ffffff" halo-radius="1.5" ><![CDATA[[name_en]]]></ShieldSymbolizer>
  </Rule>
</Style>
<Style name="place_label-capitals" filter-mode="first">
  <Rule>
    <MaxScaleDenominator>50000000</MaxScaleDenominator>
    <Filter>([capital] &lt;= 3) and ([ldir] = 'NW')</Filter>
    <ShieldSymbolizer dx="-4" dy="-4" file="icons/city3.png" unlock-image="true" size="12" face-name="Call Eight OT Italic" placement="point" fill="#000000" halo-fill="#ffffff" halo-radius="2" ><![CDATA[[name_en]]]></ShieldSymbolizer>
  </Rule>
  <Rule>
    <MaxScaleDenominator>50000000</MaxScaleDenominator>
    <Filter>([capital] &lt;= 3) and ([ldir] = 'SW')</Filter>
    <ShieldSymbolizer dx="-4" dy="4" file="icons/city3.png" unlock-image="true" size="12" face-name="Call Eight OT Italic" placement="point" fill="#000000" halo-fill="#ffffff" halo-radius="2" ><![CDATA[[name_en]]]></ShieldSymbolizer>
  </Rule>
  <Rule>
    <MaxScaleDenominator>50000000</MaxScaleDenominator>
    <Filter>([capital] &lt;= 3) and ([ldir] = 'SE')</Filter>
    <ShieldSymbolizer dx="4" dy="4" file="icons/city3.png" unlock-image="true" size="12" face-name="Call Eight OT Italic" placement="point" fill="#000000" halo-fill="#ffffff" halo-radius="2" ><![CDATA[[name_en]]]></ShieldSymbolizer>
  </Rule>
  <Rule>
    <MaxScaleDenominator>50000000</MaxScaleDenominator>
    <Filter>([capital] &lt;= 3) and ([ldir] = 'NE')</Filter>
    <ShieldSymbolizer dx="4" dy="-4" file="icons/city3.png" unlock-image="true" size="12" face-name="Call Eight OT Italic" placement="point" fill="#000000" halo-fill="#ffffff" halo-radius="2" ><![CDATA[[name_en]]]></ShieldSymbolizer>
  </Rule>
  <Rule>
    <MaxScaleDenominator>50000000</MaxScaleDenominator>
    <Filter>([capital] &lt;= 3) and ([ldir] = 'S')</Filter>
    <ShieldSymbolizer dy="11" file="icons/city3.png" unlock-image="true" size="12" face-name="Call Eight OT Italic" placement="point" fill="#000000" halo-fill="#ffffff" halo-radius="2" ><![CDATA[[name_en]]]></ShieldSymbolizer>
  </Rule>
  <Rule>
    <MaxScaleDenominator>50000000</MaxScaleDenominator>
    <Filter>([capital] &lt;= 3) and ([ldir] = 'N')</Filter>
    <ShieldSymbolizer dy="-11" file="icons/city3.png" unlock-image="true" size="12" face-name="Call Eight OT Italic" placement="point" fill="#000000" halo-fill="#ffffff" halo-radius="2" ><![CDATA[[name_en]]]></ShieldSymbolizer>
  </Rule>
  <Rule>
    <MaxScaleDenominator>50000000</MaxScaleDenominator>
    <Filter>([capital] &lt;= 3) and ([ldir] = 'W')</Filter>
    <ShieldSymbolizer dx="-12" file="icons/city3.png" unlock-image="true" size="12" face-name="Call Eight OT Italic" placement="point" fill="#000000" halo-fill="#ffffff" halo-radius="2" ><![CDATA[[name_en]]]></ShieldSymbolizer>
  </Rule>
  <Rule>
    <MaxScaleDenominator>50000000</MaxScaleDenominator>
    <Filter>([capital] &lt;= 3) and ([ldir] = 'E')</Filter>
    <ShieldSymbolizer dx="11" file="icons/city3.png" unlock-image="true" size="12" face-name="Call Eight OT Italic" placement="point" fill="#000000" halo-fill="#ffffff" halo-radius="2" ><![CDATA[[name_en]]]></ShieldSymbolizer>
  </Rule>
  <Rule>
    <MaxScaleDenominator>50000000</MaxScaleDenominator>
    <Filter>([capital] &lt;= 3)</Filter>
    <ShieldSymbolizer file="icons/city3.png" unlock-image="true" size="12" face-name="Call Eight OT Italic" placement="point" fill="#000000" halo-fill="#ffffff" halo-radius="2" ><![CDATA[[name_en]]]></ShieldSymbolizer>
  </Rule>
</Style>
<Layer name="place_label"
  srs="+proj=merc +a=6378137 +b=6378137 +lat_ts=0.0 +lon_0=0.0 +x_0=0.0 +y_0=0.0 +k=1.0 +units=m +nadgrids=@null +wktext +no_defs +over">
    <StyleName>place_label-capitals</StyleName>
    <StyleName>place_label-cityicon</StyleName>  </Layer>

<Layer name="water_label"
  srs="+proj=merc +a=6378137 +b=6378137 +lat_ts=0.0 +lon_0=0.0 +x_0=0.0 +y_0=0.0 +k=1.0 +units=m +nadgrids=@null +wktext +no_defs +over">
      </Layer>

<Layer name="poi_label"
  srs="+proj=merc +a=6378137 +b=6378137 +lat_ts=0.0 +lon_0=0.0 +x_0=0.0 +y_0=0.0 +k=1.0 +units=m +nadgrids=@null +wktext +no_defs +over">
      </Layer>

<Layer name="road_label"
  srs="+proj=merc +a=6378137 +b=6378137 +lat_ts=0.0 +lon_0=0.0 +x_0=0.0 +y_0=0.0 +k=1.0 +units=m +nadgrids=@null +wktext +no_defs +over">
      </Layer>

<Layer name="waterway_label"
  srs="+proj=merc +a=6378137 +b=6378137 +lat_ts=0.0 +lon_0=0.0 +x_0=0.0 +y_0=0.0 +k=1.0 +units=m +nadgrids=@null +wktext +no_defs +over">
      </Layer>

<Layer name="housenum_label"
  srs="+proj=merc +a=6378137 +b=6378137 +lat_ts=0.0 +lon_0=0.0 +x_0=0.0 +y_0=0.0 +k=1.0 +units=m +nadgrids=@null +wktext +no_defs +over">
      </Layer>

</Map>